gaarf/__init__.py
gaarf/api_clients.py
gaarf/base_query.py
gaarf/bq_executor.py
gaarf/builtin_queries.py
gaarf/exceptions.py
gaarf/parsers.py
gaarf/query_editor.py
gaarf/query_executor.py
gaarf/query_post_processor.py
gaarf/report.py
gaarf/report_fetcher.py
gaarf/simulation.py
gaarf/sql_executor.py
gaarf/utils.py
gaarf/cli/__init__.py
gaarf/cli/bq.py
gaarf/cli/gaarf.py
gaarf/cli/simulator.py
gaarf/cli/sql.py
gaarf/cli/utils.py
gaarf/executors/__init__.py
gaarf/executors/ads_executor.py
gaarf/executors/bq_executor.py
gaarf/executors/sql_executor.py
gaarf/io/__init__.py
gaarf/io/reader.py
gaarf/io/writer.py
gaarf/io/writers/__init__.py
gaarf/io/writers/bigquery_writer.py
gaarf/io/writers/console_writer.py
gaarf/io/writers/csv_writer.py
gaarf/io/writers/file_writer.py
gaarf/io/writers/json_writer.py
gaarf/io/writers/null_writer.py
gaarf/io/writers/sheets_writer.py
gaarf/io/writers/sqldb_writer.py
google_ads_api_report_fetcher-1.18.1.dist-info/METADATA
google_ads_api_report_fetcher-1.18.1.dist-info/WHEEL
google_ads_api_report_fetcher-1.18.1.dist-info/entry_points.txt
google_ads_api_report_fetcher-1.18.1.dist-info/top_level.txt
google_ads_api_report_fetcher-1.18.1.dist-info/RECORD
