Metadata-Version: 2.4
Name: google-ads-api-report-fetcher
Version: 1.18.1
Summary: Library for fetching reports from Google Ads API and saving them locally & remotely.
Author-email: "Google Inc. (gTech gPS CSE team)" <no-reply@google.com>, Andrei Markin <amarkin@google.com>, Sergei Dorogin <segy@google.com>
License: Apache 2.0
Project-URL: Homepage, https://github.com/google/ads-api-reports-fetcher
Project-URL: Documentation, https://github.com/google/ads-api-report-fetcher/tree/main/docs
Project-URL: Repository, https://github.com/google/ads-api-reports-fetcher.git
Project-URL: Issues, https://github.com/google/ads-api-report-fetcher/issues
Classifier: Programming Language :: Python :: 3 :: Only
Classifier: Programming Language :: Python :: 3.9
Classifier: Programming Language :: Python :: 3.10
Classifier: Programming Language :: Python :: 3.11
Classifier: Programming Language :: Python :: 3.12
Classifier: Programming Language :: Python :: 3.13
Classifier: Programming Language :: Python :: 3.14
Classifier: Intended Audience :: Developers
Classifier: Topic :: Software Development :: Libraries :: Python Modules
Classifier: Operating System :: OS Independent
Classifier: License :: OSI Approved :: Apache Software License
Requires-Python: >=3.9
Requires-Dist: google-ads>=25.1.0
Requires-Dist: smart_open
Requires-Dist: jinja2
Requires-Dist: python-dateutil
Requires-Dist: typing-extensions
Requires-Dist: rich
Requires-Dist: tenacity
Requires-Dist: garf-core>=1.0.1
Requires-Dist: garf-io>=1.0.0
Requires-Dist: garf-executors>=1.0.0
Provides-Extra: bq
Requires-Dist: garf-executors[bq]; extra == "bq"
Provides-Extra: pandas
Requires-Dist: pandas>=1.3.4; extra == "pandas"
Provides-Extra: sqlalchemy
Requires-Dist: garf-executors[sql]; extra == "sqlalchemy"
Provides-Extra: simulator
Requires-Dist: Faker; extra == "simulator"
Provides-Extra: sheets
Requires-Dist: garf-io[sheets]; extra == "sheets"
Provides-Extra: full
Requires-Dist: google-ads-api-report-fetcher[bq,pandas,sheets,simulator,sqlalchemy]; extra == "full"
